python_compile/__init__.py
python_compile/cli.py
python_compile/compile.py
python_compile/docker_build.py
python_compile/native_build.py
python_compile/assets/debian-dockerfile
python_compile/assets/demo_http_server.py
python_compile/assets/entrypoint.sh
python_compile/assets/ubuntu22-dockerfile
python_compile/assets/windows-dockerfile
python_compile-1.0.15.dist-info/LICENSE
python_compile-1.0.15.dist-info/METADATA
python_compile-1.0.15.dist-info/WHEEL
python_compile-1.0.15.dist-info/entry_points.txt
python_compile-1.0.15.dist-info/top_level.txt
python_compile-1.0.15.dist-info/RECORD
