Metadata-Version: 2.1
Name: python-compile
Version: 1.0.15
Summary: Compiles Python to an exe
Home-page: https://github.com/zackees/python-compile
Maintainer: Zachary Vorhies
License: BSD 3-Clause License
Keywords: template-python-cmd
Classifier: Programming Language :: Python :: 3
Requires-Python: >=3.7
License-File: LICENSE
Requires-Dist: docker-run-cmd ~=1.0.14
Requires-Dist: isolated-environment >=1.3.4
Requires-Dist: pytest-xdist
